LICENSE
MANIFEST.in
README.rst
classifiers.txt
setup.cfg
setup.py
lighthouse/__init__.py
lighthouse/balancer.py
lighthouse/check.py
lighthouse/cluster.py
lighthouse/configurable.py
lighthouse/discovery.py
lighthouse/events.py
lighthouse/node.py
lighthouse/peer.py
lighthouse/pluggable.py
lighthouse/reporter.py
lighthouse/service.py
lighthouse/sockutils.py
lighthouse/writer.py
lighthouse/zookeeper.py
lighthouse.egg-info/PKG-INFO
lighthouse.egg-info/SOURCES.txt
lighthouse.egg-info/dependency_links.txt
lighthouse.egg-info/entry_points.txt
lighthouse.egg-info/pbr.json
lighthouse.egg-info/requires.txt
lighthouse.egg-info/top_level.txt
lighthouse/checks/__init__.py
lighthouse/checks/http.py
lighthouse/checks/tcp.py
lighthouse/configs/__init__.py
lighthouse/configs/handler.py
lighthouse/configs/monitor.py
lighthouse/configs/watcher.py
lighthouse/haproxy/__init__.py
lighthouse/haproxy/balancer.py
lighthouse/haproxy/config.py
lighthouse/haproxy/control.py
lighthouse/haproxy/directives.json
lighthouse/haproxy/directives.py
lighthouse/haproxy/stanzas/__init__.py
lighthouse/haproxy/stanzas/backend.py
lighthouse/haproxy/stanzas/frontend.py
lighthouse/haproxy/stanzas/meta.py
lighthouse/haproxy/stanzas/peers.py
lighthouse/haproxy/stanzas/proxy.py
lighthouse/haproxy/stanzas/section.py
lighthouse/haproxy/stanzas/stanza.py
lighthouse/haproxy/stanzas/stats.py
lighthouse/log/__init__.py
lighthouse/log/cli.py
lighthouse/log/config.py
lighthouse/log/context.py
lighthouse/redis/__init__.py
lighthouse/redis/check.py
lighthouse/scripts/__init__.py
lighthouse/scripts/reporter.py
lighthouse/scripts/writer.py