Metadata-Version: 1.1
Name: lighthouse
Version: 1.0.0
Summary: Service discovery tool focused on ease-of-use and resiliency
Home-page: http://github.com/wglass/lighthouse
Author: William Glass
Author-email: william.glass@gmail.com
License: Apache
Platform: UNKNOWN
Classifier: Development Status :: 5 - Production/Stable
